LICENSE
MANIFEST.in
README.md
setup.cfg
setup.py
avt/.gitignore
avt/__init__.py
avt/version.py
avt.egg-info/PKG-INFO
avt.egg-info/SOURCES.txt
avt.egg-info/dependency_links.txt
avt.egg-info/not-zip-safe
avt.egg-info/requires.txt
avt.egg-info/top_level.txt